{
	"configurations" : 
	[
		{
			"directories" : 
			[
				{
					"build" : ".",
					"hasInstallRule" : true,
					"jsonFile" : "directory-.-Release-3fe3454d5fdc6c025094.json",
					"minimumCMakeVersion" : 
					{
						"string" : "3.12"
					},
					"projectIndex" : 0,
					"source" : ".",
					"targetIndexes" : 
					[
						0,
						1,
						2,
						3
					]
				}
			],
			"name" : "Release",
			"projects" : 
			[
				{
					"directoryIndexes" : 
					[
						0
					],
					"name" : "ign_sim_pointcloud_tool",
					"targetIndexes" : 
					[
						0,
						1,
						2,
						3
					]
				}
			],
			"targets" : 
			[
				{
					"directoryIndex" : 0,
					"id" : "ign_sim_pointcloud_tool::@6890427a1f51a3e7e1df",
					"jsonFile" : "target-ign_sim_pointcloud_tool-Release-dc418dc0224e9bd06890.json",
					"name" : "ign_sim_pointcloud_tool",
					"projectIndex" : 0
				},
				{
					"directoryIndex" : 0,
					"id" : "ign_sim_pointcloud_tool_node::@6890427a1f51a3e7e1df",
					"jsonFile" : "target-ign_sim_pointcloud_tool_node-Release-021078c39824a515b7de.json",
					"name" : "ign_sim_pointcloud_tool_node",
					"projectIndex" : 0
				},
				{
					"directoryIndex" : 0,
					"id" : "ign_sim_pointcloud_tool_uninstall::@6890427a1f51a3e7e1df",
					"jsonFile" : "target-ign_sim_pointcloud_tool_uninstall-Release-ec125a6b8d9eacdaecf3.json",
					"name" : "ign_sim_pointcloud_tool_uninstall",
					"projectIndex" : 0
				},
				{
					"directoryIndex" : 0,
					"id" : "uninstall::@6890427a1f51a3e7e1df",
					"jsonFile" : "target-uninstall-Release-12f145b9fa46057edb12.json",
					"name" : "uninstall",
					"projectIndex" : 0
				}
			]
		}
	],
	"kind" : "codemodel",
	"paths" : 
	{
		"build" : "/home/chairman/working/ros2/beijixiong/pb2025_ws/build/ign_sim_pointcloud_tool",
		"source" : "/home/chairman/working/ros2/beijixiong/pb2025_ws/src/pb2025_sentry_nav/ign_sim_pointcloud_tool"
	},
	"version" : 
	{
		"major" : 2,
		"minor" : 3
	}
}
