{
	"configurations" : 
	[
		{
			"directories" : 
			[
				{
					"build" : ".",
					"hasInstallRule" : true,
					"jsonFile" : "directory-.-Release-418a9f784126b65ec3ed.json",
					"minimumCMakeVersion" : 
					{
						"string" : "3.12"
					},
					"projectIndex" : 0,
					"source" : ".",
					"targetIndexes" : 
					[
						0,
						1,
						2,
						3
					]
				}
			],
			"name" : "Release",
			"projects" : 
			[
				{
					"directoryIndexes" : 
					[
						0
					],
					"name" : "sensor_scan_generation",
					"targetIndexes" : 
					[
						0,
						1,
						2,
						3
					]
				}
			],
			"targets" : 
			[
				{
					"directoryIndex" : 0,
					"id" : "sensor_scan_generation::@6890427a1f51a3e7e1df",
					"jsonFile" : "target-sensor_scan_generation-Release-fa966f1244c91a74acba.json",
					"name" : "sensor_scan_generation",
					"projectIndex" : 0
				},
				{
					"directoryIndex" : 0,
					"id" : "sensor_scan_generation_node::@6890427a1f51a3e7e1df",
					"jsonFile" : "target-sensor_scan_generation_node-Release-cf0b892ede850f88d1de.json",
					"name" : "sensor_scan_generation_node",
					"projectIndex" : 0
				},
				{
					"directoryIndex" : 0,
					"id" : "sensor_scan_generation_uninstall::@6890427a1f51a3e7e1df",
					"jsonFile" : "target-sensor_scan_generation_uninstall-Release-09177229a52dc3bd1746.json",
					"name" : "sensor_scan_generation_uninstall",
					"projectIndex" : 0
				},
				{
					"directoryIndex" : 0,
					"id" : "uninstall::@6890427a1f51a3e7e1df",
					"jsonFile" : "target-uninstall-Release-3d9a0f4419afade3dbb8.json",
					"name" : "uninstall",
					"projectIndex" : 0
				}
			]
		}
	],
	"kind" : "codemodel",
	"paths" : 
	{
		"build" : "/home/chairman/working/ros2/beijixiong/pb2025_ws/build/sensor_scan_generation",
		"source" : "/home/chairman/working/ros2/beijixiong/pb2025_ws/src/pb2025_sentry_nav/sensor_scan_generation"
	},
	"version" : 
	{
		"major" : 2,
		"minor" : 3
	}
}
